{
    "toolchains_binary-utilities_filePaths": {
        "arm_none_eabi": {
        "map_path": "D:\\gcc_arm_none_eabi\\gcc-arm-none-eabi-10.3-2021.10-win32\\Unit3_Revision\\HC-05_UART\\DMA_Project.map",
        "elf_path": "D:\\gcc_arm_none_eabi\\gcc-arm-none-eabi-10.3-2021.10-win32\\Unit3_Revision\\HC-05_UART\\DMA_Project.elf",
        "linkerScript_path": "D:\\gcc_arm_none_eabi\\gcc-arm-none-eabi-10.3-2021.10-win32\\Unit3_Revision\\HC-05_UART\\linker_script.ld",
        "binary_file_path": "D:\\gcc_arm_none_eabi\\gcc-arm-none-eabi-10.3-2021.10-win32\\Unit3_Revision\\HC-05_UART\\DMA_Project.elf",
        "nm_path": "D:\\gcc_arm_none_eabi\\gcc-arm-none-eabi-10.3-2021.10-win32\\gcc-arm-none-eabi-10.3-2021.10\\bin\\arm-none-eabi-gcc-nm.exe",
        "objdump_path": "D:\\gcc_arm_none_eabi\\gcc-arm-none-eabi-10.3-2021.10-win32\\gcc-arm-none-eabi-10.3-2021.10\\bin\\arm-none-eabi-objdump.exe",
        "readelf_path": "D:\\gcc_arm_none_eabi\\gcc-arm-none-eabi-10.3-2021.10-win32\\gcc-arm-none-eabi-10.3-2021.10\\bin\\arm-none-eabi-readelf.exe",
        "nm_objects_txt": "D:\\gcc_arm_none_eabi\\Madonna_MemUsageScript\\Madonna_MemUsageScript",
        "output_map_path": "D:\\gcc_arm_none_eabi\\Madonna_MemUsageScript\\Madonna_MemUsageScript\\output_map_file.txt",
        "size_utility_path": "D:\\gcc_arm_none_eabi\\gcc-arm-none-eabi-10.3-2021.10-win32\\gcc-arm-none-eabi-10.3-2021.10\\bin\\arm-none-eabi-size.exe",
        "strip_utility_path": "D:\\gcc_arm_none_eabi\\gcc-arm-none-eabi-10.3-2021.10-win32\\gcc-arm-none-eabi-10.3-2021.10\\bin\\arm-none-eabi-strip.exe",
        "addr2line_path": "D:\\gcc_arm_none_eabi\\gcc-arm-none-eabi-10.3-2021.10-win32\\gcc-arm-none-eabi-10.3-2021.10\\bin\\arm-none-eabi-addr2line.exe"

        },
        "tricore": {
         "map_path": "C:\\Users\\DELL\\htc-workspace\\tc27x_bsp_example\\_iROM_TC27X_TRIBOARD_TC2X7_V1_0\\tc27x_bsp_example.map",
         "elf_path": "C:\\Users\\DELL\\htc-workspace\\tc27x_bsp_example\\_iROM_TC27X_TRIBOARD_TC2X7_V1_0\\tc27x_bsp_example.elf",
         "linkerScript_path": "C:\\Users\\DELL\\htc-workspace\\tc27x_bsp_example\\ld\\tc27x_memory.ld",
         "binary_file_path": "C:\\Users\\DELL\\htc-workspace\\tc27x_bsp_example\\_iROM_TC27X_TRIBOARD_TC2X7_V1_0\\tc27x_bsp_example.elf",
         "nm_path": "D:\\HighTecTricore_EntryToolChain\\toolchains\\tricore\\v4.9.3.0-infineon-1.0\\bin\\tricore-nm.exe",
         "objdump_path": "D:\\HighTecTricore_EntryToolChain\\toolchains\\tricore\\v4.9.3.0-infineon-1.0\\bin\\tricore-objdump.exe",
         "readelf_path": "D:\\HighTecTricore_EntryToolChain\\toolchains\\tricore\\v4.9.3.0-infineon-1.0\\bin\\tricore-readelf.exe",
         "size_utility_path": "D:\\HighTecTricore_EntryToolChain\\toolchains\\tricore\\v4.9.3.0-infineon-1.0\\bin\\tricore-size.exe",
         "strip_utility_path": "D:\\HighTecTricore_EntryToolChain\\toolchains\\tricore\\v4.9.3.0-infineon-1.0\\bin\\tricore-strip.exe",
         "addr2line_path": "D:\\HighTecTricore_EntryToolChain\\toolchains\\tricore\\v4.9.3.0-infineon-1.0\\bin\\tricore-addr2line.exe"
        },
        "ti_cgt_tms470": {
         "map_path": "D:\\Interrupt_driver_tivac\\HC-05_UART\\Debug\\HC-05_UART.map",
         "elf_path": "D:\\Interrupt_driver_tivac\\HC-05_UART\\Debug\\HC-05_UART.out",
         "linkerScript_path": "D:\\Interrupt_driver_tivac\\HC-05_UART\\tm4c123gh6pm.cmd",
         "binary_file_path": "D:\\Interrupt_driver_tivac\\HC-05_UART\\Debug\\HC-05_UART.out",
         "nm_path": "D:\\CodeComposer\\ccs\\tools\\compiler\\ti-cgt-arm_20.2.7.LTS\\bin\\bin\\armnm.exe",
         "objdump_path": "D:\\CodeComposer\\ccs\\tools\\compiler\\ti-cgt-arm_20.2.7.LTS\\bin\\armobjdump.exe",
         "readelf_path": "D:\\CodeComposer\\ccs\\tools\\compiler\\ti-cgt-arm_20.2.7.LTS\\bin\\bin\\armreadelf.exe",
         "size_utility_path": "D:\\CodeComposer\\ccs\\tools\\compiler\\ti-cgt-arm_20.2.7.LTS\\bin\\armsize.exe",
         "strip_utility_path": "D:\\CodeComposer\\ccs\\tools\\compiler\\ti-cgt-arm_20.2.7.LTS\\bin\\bin\\armstrip.exe",
         "addr2line_path": "D:\\HighTecTricore_EntryToolChain\\toolchains\\tricore\\v4.9.3.0-infineon-1.0\\bin\\tricore-addr2line.exe"
        },
      "ti_cgt_armllvm": {
         "map_path": "D:\\Interrupt_driver_tivac\\HC-05_UART\\Debug\\HC-05_UART.map",
         "elf_path": "D:\\Interrupt_driver_tivac\\System Control\\Debug__TICLANG\\SystemControl.out",
         "linkerScript_path": "D:\\Interrupt_driver_tivac\\System Control\\tm4c123gh6pm.cmd",
         "binary_file_path": "D:\\Interrupt_driver_tivac\\HC-05_UART\\Debug\\HC-05_UART.out",
         "nm_path": "D:\\CodeComposer\\ccs\\tools\\compiler\\ti-cgt-arm_20.2.7.LTS\\bin\\bin\\armnm.exe",
         "objdump_path": "D:\\CodeComposer\\ccs\\tools\\compiler\\ti-cgt-armllvm_2.1.2.LTS\\bin\\tiarmobjdump.exe",
         "readelf_path": "D:\\CodeComposer\\ccs\\tools\\compiler\\ti-cgt-arm_20.2.7.LTS\\bin\\bin\\armreadelf.exe",
         "size_utility_path": "D:\\CodeComposer\\ccs\\tools\\compiler\\ti-cgt-armllvm_2.1.2.LTS\\bin\\tiarmsize.exe",
         "strip_utility_path": "D:\\CodeComposer\\ccs\\tools\\compiler\\ti-cgt-armllvm_2.1.2.LTS\\bin\\tiarmstrip.exe",
         "addr2line_path": "D:\\HighTecTricore_EntryToolChain\\toolchains\\tricore\\v4.9.3.0-infineon-1.0\\bin\\tricore-addr2line.exe"
      }
    },
    "toolchains_output_files": {
        "arm_none_eabi": {
            "map_file_parsing_csv": "Mapfile_Parsing_arm_none_eabi.csv",
            "nm_objects_file_txt": "nm_Objects_arm_none_eabi.txt",
            "elf_objects_file_csv": "elf_Objects_arm_none_eabi.csv",
            "linked_memory_file_csv": "Linked_Memory_arm_none_eabi.csv",
            "mismatch_memory_file_csv": "Linked_Mismatch_arm_none_eabi.csv",
            "memory_usage_file_csv": "Memory_consumption_arm_none_eabi.csv",
            "assembly_file_txt": "Assembly_Output.txt",
            "size_sections_file_txt": "SizeOutput.txt",
            "addr2line_file_txt": "Addr2line.txt",
            "stripped_file_elf": "StrippedElf.elf"
        },
        "tricore": {
            "map_file_parsing_csv": "Mapfile_Parsing_tricore.csv",
            "nm_objects_file_txt": "nm_Objects_tricore.txt",
            "elf_objects_file_csv": "elf_Objects_tricore.csv",
            "linked_memory_file_csv": "Linked_Memory_tricore.csv",
            "mismatch_memory_file_csv": "Linked_Mismatch_tricore.csv",
            "memory_usage_file_csv": "Memory_consumption_tricore.csv",
            "assembly_file_txt": "HighTech_Assembly_Output.txt",
            "size_sections_file_txt": "HighTech_SizeOutput.txt",
            "addr2line_file_txt": "HighTech_addr2line.txt",
            "stripped_file_elf": "HighTech_StrippedElf.elf"
        },
      "ti_cgt_tms470": {
            "map_file_parsing_csv": "Mapfile_Parsing_ti_cgt_tms470.csv",
            "nm_objects_file_txt": "nm_Objects_ti_cgt_tms470.txt",
            "elf_objects_file_csv": "elf_Objects_ti_cgt_tms470.csv",
            "linked_memory_file_csv": "Linked_Memory_ti_cgt_tms470.csv",
            "mismatch_memory_file_csv": "Linked_Mismatch_ti_cgt_tms470.csv",
            "memory_usage_file_csv": "Memory_consumption_ti_cgt_tms470.csv",
            "assembly_file_txt": "ti_cgt_tms470_Assembly_Output.txt",
            "size_sections_file_txt": "ti_cgt_tms470_SizeOutput.txt",
            "addr2line_file_txt": "ti_cgt_tms470_addr2line.txt",
            "stripped_file_elf": "ti_cgt_tms470_StrippedElf.out"
      },
      "ti_cgt_armllvm": {
            "map_file_parsing_csv": "Mapfile_Parsing_ti_cgt_armllvm.csv",
            "nm_objects_file_txt": "nm_Objects_ti_cgt_armllvm.txt",
            "elf_objects_file_csv": "elf_Objects_ti_cgt_armllvm.csv",
            "linked_memory_file_csv": "Linked_Memory_ti_cgt_armllvm.csv",
            "mismatch_memory_file_csv": "Linked_Mismatch_ti_cgt_armllvm.csv",
            "memory_usage_file_csv": "Memory_consumption_ti_cgt_armllvm.csv",
            "assembly_file_txt": "ti_cgt_armllvm_Assembly_Output.txt",
            "size_sections_file_txt": "ti_cgt_armllvm_SizeOutput.txt",
            "addr2line_file_txt": "ti_cgt_armllvm_addr2line.txt",
            "stripped_file_elf": "ti_cgt_armllvm_StrippedElf.out"
      }
    },

    "gnu_commands": {
        "nm_command_elf": "{nm_path} {nm_flags} {elf_file_path} > {nm_objects_txt}",
        "nm_command_out": "{nm_path} {nm_flags} {out_file_path} > {nm_objects_txt}",
        "nm_command":     "{nm_path} {nm_flags} {binary_file_path} > {nm_objects_txt}",
        "objdump_command": "{objdump_path} {objdump_flags} {binary_file_path} > {Assembly_txt}",
        "readelf_command": "{readelf_path} {readelf_flags} {binary_file_path}",
        "size_command": "{size_path} {size_flags} {binary_file_path} > {SizeFile_txt} ",
        "strip_command": "{strip_path} {strip_flags} {binary_file_path} {strip_output_flag} {stripped_elf}",
        "addr2line_command": "{addr2line_Path} {ExecutableName_flag}{binary_file_path} {flags} {HexadecimalAddress} > {addr2line_Output_txt}"
    },

    "toolchains_command_flags": {
    "gnu_command_flags": {
        "NM_flags": {
            "defined_only": "--defined-only",
            "print_size": "--print-size"
        },
        "ObjDump_flags": {
        "SourceCodeIntermixedDisassembly": "-S",
        "SectionHeaders": "-h",
        "All_Headers": "-x",
        "Disassemble": "-d",
        "DisassembleAll": "-D",
        "SymbolTable": "-t",
        "DynamicSymbolTable": "-T"
        },
        "Size_flags": {
        "format": "-A",
        "SizeHexaDecimal": "-x"
        },
        "Strip_flags": {
        "RemoveDebugging": "-g",
        "RemoveUnneededSymbols": "--strip-unneeded",
        "OutputFile": "-o"
       },
        "Addr2line_flags": {
        "DisplayFunctionName": "-f",
        "StripDirectoryName": "-s",
        "ExecutableName": "--exe="
      }
    }
}
}